MANIFEST.in
setup.cfg
setup.py
zopy/__init__.py
zopy/core.py
zopy/crm.py
zopy/schemas.py
zopy/test.py
zopy.egg-info/PKG-INFO
zopy.egg-info/SOURCES.txt
zopy.egg-info/dependency_links.txt
zopy.egg-info/requires.txt
zopy.egg-info/top_level.txt