Metadata-Version: 1.1
Name: zopy
Version: 0.4.0
Summary: Zoho API integration for Python
Home-page: https://github.com/dhararon/zopy
Author: Dharwin Perez
Author-email: dhararon@hotmail.com
License: MIT license
Download-URL: https://github.com/dhararon/Zopy/tarball/master
Keywords: crm,CRM,zoho
Platform: UNKNOWN
